jupyterlab_tabnine/__init__.py
jupyterlab_tabnine/_version.py
jupyterlab_tabnine/handler.py
jupyterlab_tabnine/tabnine.py
jupyterlab_tabnine/labextension/package.json
jupyterlab_tabnine/labextension/schemas/@tabnine/jupyterlab/package.json.orig
jupyterlab_tabnine/labextension/static/194.2351e99d4be5cf358d5e.js
jupyterlab_tabnine/labextension/static/249.9e6a2b9ff8d4924cfb66.js
jupyterlab_tabnine/labextension/static/631.d72d4e7a29f7765da176.js
jupyterlab_tabnine/labextension/static/remoteEntry.22756925e4c902776088.js
jupyterlab_tabnine/labextension/static/style.js
jupyterlab_tabnine/labextension/static/third-party-licenses.json
jupyterlab_tabnine-0.0.24.data/data/etc/jupyter/jupyter_notebook_config.d/jupyterlab_tabnine.json
jupyterlab_tabnine-0.0.24.data/data/etc/jupyter/jupyter_server_config.d/jupyterlab_tabnine.json
jupyterlab_tabnine-0.0.24.data/data/share/jupyter/labextensions/@tabnine/jupyterlab/install.json
jupyterlab_tabnine-0.0.24.data/data/share/jupyter/labextensions/@tabnine/jupyterlab/package.json
jupyterlab_tabnine-0.0.24.data/data/share/jupyter/labextensions/@tabnine/jupyterlab/schemas/@tabnine/jupyterlab/package.json.orig
jupyterlab_tabnine-0.0.24.data/data/share/jupyter/labextensions/@tabnine/jupyterlab/static/194.2351e99d4be5cf358d5e.js
jupyterlab_tabnine-0.0.24.data/data/share/jupyter/labextensions/@tabnine/jupyterlab/static/249.9e6a2b9ff8d4924cfb66.js
jupyterlab_tabnine-0.0.24.data/data/share/jupyter/labextensions/@tabnine/jupyterlab/static/631.d72d4e7a29f7765da176.js
jupyterlab_tabnine-0.0.24.data/data/share/jupyter/labextensions/@tabnine/jupyterlab/static/remoteEntry.22756925e4c902776088.js
jupyterlab_tabnine-0.0.24.data/data/share/jupyter/labextensions/@tabnine/jupyterlab/static/style.js
jupyterlab_tabnine-0.0.24.data/data/share/jupyter/labextensions/@tabnine/jupyterlab/static/third-party-licenses.json
jupyterlab_tabnine-0.0.24.dist-info/METADATA
jupyterlab_tabnine-0.0.24.dist-info/WHEEL
jupyterlab_tabnine-0.0.24.dist-info/top_level.txt
jupyterlab_tabnine-0.0.24.dist-info/RECORD
