Metadata-Version: 2.1
Name: jupyterlab-tabnine
Version: 0.0.24
Summary: JupyterLab client for Tabnine
Home-page: https://github.com/codota/tabnine-jupyterlab
Author: Tabnine
Author-email: info@tabnine.com
License: BSD-3-Clause
Keywords: Jupyter,JupyterLab,JupyterLab3,Tabnine,python
Platform: Linux
Platform: Mac OS X
Platform: Windows
Classifier: License :: OSI Approved :: BSD License
Classifier: Programming Language :: Python
Classifier: Programming Language :: Python :: 3
Classifier: Programming Language :: Python :: 3.6
Classifier: Programming Language :: Python :: 3.7
Classifier: Programming Language :: Python :: 3.8
Classifier: Programming Language :: Python :: 3.9
Classifier: Framework :: Jupyter
Requires-Python: >=3.6
